pgtrigger/__init__.py
pgtrigger/apps.py
pgtrigger/compiler.py
pgtrigger/contrib.py
pgtrigger/core.py
pgtrigger/features.py
pgtrigger/installation.py
pgtrigger/management/__init__.py
pgtrigger/management/commands/__init__.py
pgtrigger/management/commands/pgtrigger.py
pgtrigger/migrations.py
pgtrigger/models.py
pgtrigger/py.typed
pgtrigger/registry.py
pgtrigger/runtime.py
pgtrigger/utils.py
pgtrigger/version.py
django_pgtrigger-4.15.3.dist-info/LICENSE
django_pgtrigger-4.15.3.dist-info/METADATA
django_pgtrigger-4.15.3.dist-info/WHEEL
django_pgtrigger-4.15.3.dist-info/RECORD
