Metadata-Version: 2.1
Name: django-pgtrigger
Version: 4.15.3
Summary: Postgres trigger support integrated with Django models.
Home-page: https://github.com/AmbitionEng/django-pgtrigger
License: BSD-3-Clause
Author: Wes Kendall
Requires-Python: >=3.9.0,<4
Classifier: Framework :: Django
Classifier: Framework :: Django :: 4.2
Classifier: Framework :: Django :: 5.0
Classifier: Framework :: Django :: 5.1
Classifier: Framework :: Django :: 5.2
Classifier: Intended Audience :: Developers
Classifier: License :: OSI Approved :: BSD License
Classifier: Operating System :: OS Independent
Classifier: Programming Language :: Python
Classifier: Programming Language :: Python :: 3
Classifier: Programming Language :: Python :: 3.9
Classifier: Programming Language :: Python :: 3.10
Classifier: Programming Language :: Python :: 3.11
Classifier: Programming Language :: Python :: 3.12
Classifier: Programming Language :: Python :: 3.13
Classifier: Programming Language :: Python :: 3 :: Only
Requires-Dist: django (>=4)
Project-URL: Documentation, https://django-pgtrigger.readthedocs.io
Project-URL: Repository, https://github.com/AmbitionEng/django-pgtrigger
